joplin_mcp/__init__.py
joplin_mcp/__main__.py
joplin_mcp/config.py
joplin_mcp/content_utils.py
joplin_mcp/fastmcp_server.py
joplin_mcp/formatting.py
joplin_mcp/install.py
joplin_mcp/install_embedded.py
joplin_mcp/notebook_utils.py
joplin_mcp/py.typed
joplin_mcp/server.py
joplin_mcp/ui_integration.py
joplin_mcp/imports/__init__.py
joplin_mcp/imports/engine.py
joplin_mcp/imports/tools.py
joplin_mcp/imports/types.py
joplin_mcp/imports/importers/__init__.py
joplin_mcp/imports/importers/base.py
joplin_mcp/imports/importers/csv_importer.py
joplin_mcp/imports/importers/generic_importer.py
joplin_mcp/imports/importers/html_importer.py
joplin_mcp/imports/importers/jex_importer.py
joplin_mcp/imports/importers/markdown_importer.py
joplin_mcp/imports/importers/raw_importer.py
joplin_mcp/imports/importers/utils/__init__.py
joplin_mcp/imports/importers/utils/content_processors.py
joplin_mcp/imports/importers/utils/detectors.py
joplin_mcp/imports/importers/utils/file_utils.py
joplin_mcp/imports/importers/utils/timestamp_utils.py
joplin_mcp/tools/__init__.py
joplin_mcp/tools/notebooks.py
joplin_mcp/tools/notes.py
joplin_mcp/tools/tags.py
joplin_mcp/types/__init__.py
joplin_mcp-0.5.0.dist-info/licenses/LICENSE
joplin_mcp-0.5.0.dist-info/METADATA
joplin_mcp-0.5.0.dist-info/WHEEL
joplin_mcp-0.5.0.dist-info/entry_points.txt
joplin_mcp-0.5.0.dist-info/top_level.txt
joplin_mcp-0.5.0.dist-info/RECORD
