Metadata-Version: 2.4
Name: joplin-mcp
Version: 0.5.0
Summary: Model Context Protocol (MCP) server for Joplin note-taking application
Author: Alon Diament
Maintainer: Alon Diament
License: MIT License
Project-URL: Homepage, https://github.com/alondmnt/joplin-mcp
Project-URL: Documentation, https://github.com/alondmnt/joplin-mcp/blob/main/README.md
Project-URL: Repository, https://github.com/alondmnt/joplin-mcp
Project-URL: Issues, https://github.com/alondmnt/joplin-mcp/issues
Keywords: joplin,mcp,model-context-protocol,notes,ai,assistant
Classifier: Development Status :: 3 - Alpha
Classifier: Intended Audience :: Developers
Classifier: License :: OSI Approved :: MIT License
Classifier: Operating System :: OS Independent
Classifier: Programming Language :: Python :: 3
Classifier: Programming Language :: Python :: 3.10
Classifier: Programming Language :: Python :: 3.11
Classifier: Programming Language :: Python :: 3.12
Classifier: Topic :: Software Development :: Libraries :: Python Modules
Classifier: Topic :: Text Processing
Classifier: Topic :: Office/Business
Requires-Python: >=3.10
License-File: LICENSE
Requires-Dist: mcp<2,>=1
Requires-Dist: joppy>=1.0.0
Requires-Dist: fastmcp<3,>=2
Requires-Dist: pydantic<3,>=2
Requires-Dist: httpx<1,>=0.24
Requires-Dist: typing-extensions>=4.0.0
Requires-Dist: PyYAML>=6.0.0
Requires-Dist: beautifulsoup4>=4.9.0
Requires-Dist: markdownify>=0.11.0
Provides-Extra: dev
Requires-Dist: pytest>=7.0.0; extra == "dev"
Requires-Dist: pytest-asyncio>=0.21.0; extra == "dev"
Requires-Dist: pytest-mock>=3.10.0; extra == "dev"
Requires-Dist: pytest-cov>=4.0.0; extra == "dev"
Requires-Dist: black>=23.0.0; extra == "dev"
Requires-Dist: mypy>=1.0.0; extra == "dev"
Requires-Dist: ruff>=0.1.0; extra == "dev"
Requires-Dist: coverage>=7.0.0; extra == "dev"
Requires-Dist: pre-commit>=3.0.0; extra == "dev"
Provides-Extra: docs
Requires-Dist: mkdocs>=1.4.0; extra == "docs"
Requires-Dist: mkdocs-material>=8.0.0; extra == "docs"
Requires-Dist: mkdocstrings[python]>=0.20.0; extra == "docs"
Dynamic: license-file
